quickscale/__init__.py
quickscale-0.73.0.dist-info/METADATA
quickscale-0.73.0.dist-info/WHEEL
quickscale-0.73.0.dist-info/RECORD
