Metadata-Version: 2.4
Name: quickscale
Version: 0.73.0
Summary: Meta-package that installs quickscale-core and quickscale-cli together
License: Apache-2.0
Keywords: django,cli,scaffolding,project-generator
Author: Experto AI
Author-email: victor@experto.ai
Requires-Python: >=3.12,<4.0
Classifier: License :: OSI Approved :: Apache Software License
Classifier: Programming Language :: Python :: 3
Classifier: Programming Language :: Python :: 3.12
Classifier: Programming Language :: Python :: 3.13
Classifier: Programming Language :: Python :: 3.14
Requires-Dist: quickscale-cli (>=0.73.0,<0.74.0)
Requires-Dist: quickscale-core (>=0.73.0,<0.74.0)
Project-URL: Documentation, https://github.com/Experto-AI/quickscale/tree/main/docs
Project-URL: Homepage, https://github.com/Experto-AI/quickscale
Project-URL: Repository, https://github.com/Experto-AI/quickscale
